Workbook

Sheet Annahmen
A1: CreativeCinema GmbH – Marketingplan 2026/27 – Annahmen
A3: Annahme | B3: Wert | C3: Quelle / Kommentar
A4: Umsatz Ist (Basis) | B4: 500000 | C4: Angabe Geschäftsführung
A5: Umsatzziel (24 Monate) | B5: 700000 | C5: Wachstumsstrategie, 3 Hebel
A6: Ziel-EBIT-Marge | B6: 0.3 | C6: Vorgabe Geschäftsführung
A7: Marketingbudget (% v. Umsatz Ist) | B7: 0.048 | C7: Branchenüblich 4–5 % bei EBIT-Disziplin
A8: Ziel Kosten pro qualifiziertem Lead | B8: 300 | C8: Steuerungsgröße
A9: Ziel Vermietungstage / Jahr | B9: 45 | C9: Hebel 1: Studiovermietung
A10: Ziel Retainer-Kunden (Ende Jahr 1) | B10: 4 | C10: Hebel 2: Content-Abos
A11: Ø Retainer-Wert / Monat | B11: 2500 | C11: Hebel 2
A12: Ø Tagessatz Studiovermietung | B12: 2500 | C12: Hebel 1
A13: Jahres-Marketingbudget | B13: =B4*B7 -> 24000 | C13: Formel: Umsatz Ist × Budgetquote

Sheet Monatsbudget
A1: Monatsbudget nach Kanal (alle Werte in €)
A3: Kanal / Maßnahme | B3: Hebel | C3: Jan | D3: Feb | E3: Mär | F3: Apr | G3: Mai | H3: Jun | I3: Jul | J3: Aug | K3: Sep | L3: Okt | M3: Nov | N3: Dez | O3: Summe | P3: Anteil
A4: LINKEDIN
A5: LinkedIn Ads (Thought-Leader auf Entscheider) | B5: 2 Retainer | C5: 300 | D5: 300 | E5: 500 | F5: 600 | G5: 600 | H5: 600 | I5: 600 | J5: 500 | K5: 800 | L5: 800 | M5: 800 | N5: 800 | O5: =SUM(C5:N5) -> 7200 | P5: =O5/$O$18 -> 0.30050083
A6: Content-Boost Demo-Film / Rechner-Kampagne | B6: 2+3 | C6: 0 | D6: 0 | E6: 0 | F6: 0 | G6: 300 | H6: 300 | I6: 300 | J6: 300 | K6: 200 | L6: 200 | M6: 200 | N6: 200 | O6: =SUM(C6:N6) -> 2000 | P6: =O6/$O$18 -> 0.083472454
A7: GOOGLE ADS
A8: Mietkeywords (LED Studio mieten etc.) | B8: 1 Vermietung | C8: 400 | D8: 400 | E8: 400 | F8: 400 | G8: 400 | H8: 400 | I8: 400 | J8: 400 | K8: 400 | L8: 400 | M8: 400 | N8: 400 | O8: =SUM(C8:N8) -> 4800 | P8: =O8/$O$18 -> 0.20033389
A9: Nischen-Keywords (Virtual Production, XR) | B9: 3 Projekte | C9: 0 | D9: 100 | E9: 100 | F9: 150 | G9: 150 | H9: 150 | I9: 150 | J9: 150 | K9: 200 | L9: 200 | M9: 250 | N9: 200 | O9: =SUM(C9:N9) -> 1800 | P9: =O9/$O$18 -> 0.075125209
A10: EVENTS & NETZWERKE
A11: Open-Studio-Tag (Catering, Einladungen) | B11: 1+2 | C11: 0 | D11: 0 | E11: 400 | F11: 0 | G11: 0 | H11: 400 | I11: 0 | J11: 0 | K11: 400 | L11: 0 | M11: 0 | N11: 400 | O11: =SUM(C11:N11) -> 1600 | P11: =O11/$O$18 -> 0.066777963
A12: Mitgliedschaften (Marketing Club, BVMW, IHK) | B12: 2+3 | C12: 900 | D12: 0 | E12: 0 | F12: 0 | G12: 0 | H12: 0 | I12: 600 | J12: 0 | K12: 0 | L12: 0 | M12: 0 | N12: 0 | O12: =SUM(C12:N12) -> 1500 | P12: =O12/$O$18 -> 0.062604341
A13: Messe-Mailings + Vor-Ort-Aktionen (SPS, ew) | B13: 3 Projekte | C13: 0 | D13: 200 | E13: 0 | F13: 0 | G13: 0 | H13: 0 | I13: 0 | J13: 0 | K13: 300 | L13: 300 | M13: 300 | N13: 0 | O13: =SUM(C13:N13) -> 1100 | P13: =O13/$O$18 -> 0.04590985
A14: WEB, SEO & TOOLS
A15: Landingpages (Pakete, Mietseite, Rechner) | B15: 1+2+3 | C15: 400 | D15: 400 | E15: 0 | F15: 600 | G15: 600 | H15: 0 | I15: 0 | J15: 0 | K15: 0 | L15: 0 | M15: 0 | N15: 0 | O15: =SUM(C15:N15) -> 2000 | P15: =O15/$O$18 -> 0.083472454
A16: SEO-Pflege, Verzeichnisse, Locationguides | B16: 1+3 | C16: 100 | D16: 100 | E16: 100 | F16: 100 | G16: 100 | H16: 100 | I16: 100 | J16: 100 | K16: 100 | L16: 100 | M16: 0 | N16: 0 | O16: =SUM(C16:N16) -> 1000 | P16: =O16/$O$18 -> 0.041736227
A17: Tools (CRM-Tracking, E-Mail, Analytics) | B17: alle | C17: 80 | D17: 80 | E17: 80 | F17: 80 | G17: 80 | H17: 80 | I17: 80 | J17: 80 | K17: 80 | L17: 80 | M17: 80 | N17: 80 | O17: =SUM(C17:N17) -> 960 | P17: =O17/$O$18 -> 0.040066778
A18: GESAMT / Monat | C18: =C5+C6+C8+C9+C11+C12+C13+C15+C16+C17 -> 2180 | D18: =D5+D6+D8+D9+D11+D12+D13+D15+D16+D17 -> 1580 | E18: =E5+E6+E8+E9+E11+E12+E13+E15+E16+E17 -> 1580 | F18: =F5+F6+F8+F9+F11+F12+F13+F15+F16+F17 -> 1930 | G18: =G5+G6+G8+G9+G11+G12+G13+G15+G16+G17 -> 2230 | H18: =H5+H6+H8+H9+H11+H12+H13+H15+H16+H17 -> 2030 | I18: =I5+I6+I8+I9+I11+I12+I13+I15+I16+I17 -> 2230 | J18: =J5+J6+J8+J9+J11+J12+J13+J15+J16+J17 -> 1530 | ... N18: =N5+N6+N8+N9+N11+N12+N13+N15+N16+N17 -> 2080 | O18: =SUM(C18:N18) -> 23960 | P18: =SUM(P4:P17) -> 1
A20: Abgleich Jahresbudget (Annahmen) | B20: =Annahmen!B4*Annahmen!B7 -> 24000
A21: Abweichung (Plan – Budget) | B21: =O18-B20 -> -40

Sheet Maßnahmenkalender
A1: Maßnahmenkalender – 12 Monate
A3: Monat | B3: Hebel | C3: Maßnahme | D3: Ziel / Ergebnis | E3: Verantwortlich | F3: Status
A4: M1 (Start) | B4: 1 | C4: Mietseite live: 'LED-Studio mieten' + Google Ads Mietkeywords starten | D4: Erste Mietanfragen ab Woche 2 | E4: GF
A5: M1 | B5: 1 | C5: Einträge Locationguide Bayern, Studioverzeichnisse, Google Business optimieren | D5: Dauerhafte Auffindbarkeit | E5: Team
A6: M1 | B6: 2 | C6: LinkedIn-Redaktionsplan: 2–3 Posts/Woche Behind-the-scenes festlegen | D6: Sichtbarkeit bei Entscheidern | E6: Team
A7: M1 | B7: alle | C7: CRM-/Lead-Tracking einrichten (Quelle je Lead, CPL messbar) | D7: Steuerbarkeit aller KPIs | E7: GF
A8: M2 | B8: 1+2 | C8: Zielliste: 150–300 Agenturen/Fotografen/Eventtechniker + 100 Industrie-Marketingleiter | D8: Vertriebsbasis steht | E8: GF
A9: M2 | B9: 3 | C9: Messe-Mailing 1 an Aussteller (Frühjahrsmessen): 'Messefilm aus dem XR-Studio' | D9: 10+ Erstgespräche | E9: GF
A10: M3 | B10: 1+2 | C10: Open-Studio-Tag #1 (Agenturen & Eventtechnik einladen) | D10: 20+ Besucher, 3+ Mietleads | E10: Team
A11: M3 | B11: 2 | C11: LinkedIn Ads hochfahren auf beste organische Posts | D11: CPL < 300 € validieren | E11: GF
A12: M4 | B12: 2+3 | C12: Produktion Demo-Film 'Was kostet ein Drehtag wirklich?' (Eigenleistung) | D12: Leuchtturm-Asset fertig | E12: Team
A13: M5 | B13: 2+3 | C13: Landingpage mit Kostenvergleichs-Rechner live + Kampagnenstart | D13: 50+ Rechner-Nutzungen/Monat | E13: GF
A14: M5 | B14: 3 | C14: Festpreis-Pakete auf Website (Recruiting-Tag, Messe-Paket, Reels-Abo) | D14: Anfragen ohne Angebots-Pingpong | E14: GF
A15: M6 | B15: 1+2 | C15: Open-Studio-Tag #2 + erster Vortrag (Marketing Club / IHK): 'Virtual Production für den Mittelstand' | D15: 5+ qualifizierte Leads | E15: GF
... A25: M12 | B25: 1+2 | C25: Open-Studio-Tag #4 / Jahresabschluss-Event | D25: Kundenbindung Retainer | E25: Team

Sheet KPIs
A1: Steuerungs-KPIs (monatlich prüfen)
A3: KPI | B3: Hebel | C3: Zielwert Jahr 1 | D3: Messung / Quelle
A4: Vermietungstage Studio | B4: 1 | C4: =Annahmen!B9 -> 45 | D4: Kalender / Rechnungen
A5: Umsatz Vermietung | B5: 1 | C5: =Annahmen!B9*Annahmen!B12 -> 112500 | D5: Tage × Ø Tagessatz
A6: Retainer-Kunden (Bestand) | B6: 2 | C6: =Annahmen!B10 -> 4 | D6: CRM
A7: Wiederkehrender Umsatz (Jahresende, p.a.) | B7: 2 | C7: =Annahmen!B10*Annahmen!B11*12 -> 120000 | D7: Kunden × Wert × 12
A8: Kosten pro qualifiziertem Lead | B8: alle | C8: =Annahmen!B8 -> 300 | D8: Marketingkosten ÷ Leads (CRM)
A9: Qualifizierte Leads / Monat | B9: alle | C9: =ROUND(Monatsbudget!O18/12/Annahmen!B8,0) -> 7 | D9: Monatsbudget ÷ Ziel-CPL
A10: Lead → Erstgespräch-Quote | B10: alle | C10: 0.4 | D10: CRM; Zielwert 40 %
A11: Anteil wiederkehrender Umsatz am Gesamtumsatz | B11: 2 | C11: =C7/Annahmen!B5 -> 0.17142857 | D11: Retainer ÷ Umsatzziel
A12: LinkedIn: Reichweite Entscheider-Zielgruppe | B12: 2 | C12: 50000 | D12: LinkedIn Analytics, Impressionen/Monat
